sbomvalidate/__init__.py
sbomvalidate/cli.py
sbomvalidate/version.py
sbomvalidate-0.1.0.dist-info/licenses/LICENSE
sbomvalidate-0.1.0.dist-info/METADATA
sbomvalidate-0.1.0.dist-info/WHEEL
sbomvalidate-0.1.0.dist-info/entry_points.txt
sbomvalidate-0.1.0.dist-info/top_level.txt
sbomvalidate-0.1.0.dist-info/RECORD
